btree.py
gui.py
pager.py
serialization.py
shell_interativo.py
marcodb-1.0.8.dist-info/METADATA
marcodb-1.0.8.dist-info/WHEEL
marcodb-1.0.8.dist-info/entry_points.txt
marcodb-1.0.8.dist-info/top_level.txt
marcodb-1.0.8.dist-info/RECORD
