Metadata-Version: 2.4
Name: marcodb
Version: 1.0.8
Summary: Um motor de banco de dados Chave-Valor (B+ Tree) escrito em Python.
Home-page: https://github.com/marconeed/MarcoDB
Author: Marco Lago Pereira
Author-email: seu.email@exemplo.com
Classifier: Programming Language :: Python :: 3
Classifier: License :: OSI Approved :: MIT License
Classifier: Operating System :: OS Independent
Classifier: Topic :: Database
Requires-Python: >=3.7
Dynamic: author
Dynamic: author-email
Dynamic: classifier
Dynamic: description
Dynamic: description-content-type
Dynamic: home-page
Dynamic: requires-python
Dynamic: summary
